actions/github/__init__.py
actions/github/context.py
actions/github/github.py
actions_python_github-0.1.3.dist-info/METADATA
actions_python_github-0.1.3.dist-info/WHEEL
actions_python_github-0.1.3.dist-info/RECORD
